Metadata-Version: 1.1
Name: sakaio
Version: 2.0
Summary: Swiss Army knife for asyncio
Home-page: https://github.com/nitely/sakaio
Author: Esteban Castro Borsani
Author-email: ecastroborsani@gmail.com
License: MIT License
Platform: UNKNOWN
Classifier: Development Status :: 5 - Production/Stable
Classifier: Environment :: Web Environment
Classifier: Intended Audience :: Developers
Classifier: License :: OSI Approved :: MIT License
Classifier: Operating System :: OS Independent
Classifier: Programming Language :: Python
Classifier: Programming Language :: Python :: 3
Classifier: Topic :: Internet :: WWW/HTTP
Classifier: Topic :: Internet :: WWW/HTTP :: Dynamic Content
